<?xml version="1.0" encoding="UTF-8"?><i><chatserver>chat.bilibili.com</chatserver><chatid>373291185</chatid><mission>0</mission><maxlimit>1000</maxlimit><state>0</state><real_name>0</real_name><source>k-v</source><d p="2.63700,1,25,16777215,1681107723,0,d352c774,1291984243899256320,10">牛爷爷打卡</d><d p="130.06300,1,25,16777215,1680834837,0,bdf5e184,1289695104847873024,10">B站到底出了多少程序员</d><d p="153.15500,1,25,16777215,1680511860,0,4f268722,1286985779331163904,10">我去这都要说吗  好傻瓜式教学</d><d p="29.46200,1,25,16777215,1680357898,0,70bec0d8,1285694253833910272,10">chenhl学vue</d><d p="4.12900,1,25,16777215,1680248153,0,4d5f443,1284773647340292864,10">好累各位</d><d p="5.27000,1,25,16777215,1680161459,0,e8abb273,1284046403546812416,10">4 b</d><d p="187.12900,1,25,16777215,1679888884,0,3dc731cf,1281759876439356928,10">ctrl+w 显示计算属性</d><d p="94.57900,1,25,16777215,1679888838,0,3dc731cf,1281759488625677568,10">ctrl+w 显示计算属性</d><d p="21.14800,1,25,16777215,1679888801,0,3dc731cf,1281759180159730432,10">那确实要起早一旦</d><d p="235.69500,1,25,16777215,1679882856,0,b31ec2af,1281709314230547200,10">但是实际上真的是韩素</d><d p="44.78300,1,25,16777215,1679669715,0,c572c653,1279921355407980032,10">小傻瓜</d><d p="123.13800,1,25,16777215,1679588034,0,96ce4ed2,1279236163302854656,10">lamda</d><d p="186.50700,1,25,16777215,1679494332,0,4a947ef8,1278450140650424064,10">后端不需要懂底层，嘿嘿</d><d p="208.16300,1,25,16777215,1679187000,0,62368ccf,1275872046282668544,10">好不规范，真不好学</d><d p="194.01100,1,25,16777215,1678980631,0,fb65a39b,1274140898879369216,10">我一开始就想这样写了</d><d p="146.39000,1,25,16777215,1678973781,0,5caf78d,1274083438852468992,10">小java干妲己</d><d p="237.41900,1,25,16777215,1678959047,0,d80d7828,1273959844440979200,10">新手学习感觉这玩意不好</d><d p="2.10700,1,25,16777215,1678804082,0,fc05718,1272659900673061120,10">赵某打卡</d><d p="1.60100,1,25,16777215,1678710257,0,1409b981,1271872836943851264,10">刘刘闯打卡！！</d><d p="92.83600,1,25,16777215,1678433022,0,e6a8b987,1269547224157957120,10">一天20集简简单单的</d><d p="19.64300,1,25,16777215,1678091679,0,98fb6ffe,1266683831998993152,10">是不是白学了啊 简写 哈哈</d><d p="250.62400,1,25,16777215,1678081686,0,5ae1307e,1266600000134089216,10">这个带缓存</d><d p="5.02000,1,25,15138834,1678024686,0,b8c02663,1266121851592281088,10">好累各位</d><d p="3.88300,1,25,16777215,1677840149,0,bae2b04e,1264573840387193600,10">黑虎阿福来学前端</d><d p="154.10200,1,25,16777215,1677759916,0,681ffcb3,1263900802670417920,10">李cc别学了</d><d p="114.32800,1,25,16777215,1677586526,0,8726be0c,1262446296115976704,10">那你还讲这么多</d><d p="251.95300,1,25,16777215,1677334166,0,82d084a0,1260329349769458176,10">我说对对对</d><d p="66.81000,1,25,16777215,1677310936,0,55c7a1d3,1260134479369116928,10">这个老师好追求完美</d><d p="120.26000,1,25,16777215,1677161647,0,7bd48c29,1258882160505420800,10">冲</d><d p="141.73400,1,25,16777215,1677128281,0,4201b847,1258602258174619648,10">alt+shift+a多行注释</d><d p="76.01000,1,25,16777215,1677128202,0,4201b847,1258601597530242304,10">shift+del删除一整行</d><d p="9.74000,1,25,16777215,1676762399,0,3a2da1ac,1255533017771154176,10">坚持十天看完vue</d><d p="264.39400,1,25,16777215,1676471822,0,8b796981,1253095483858238976,10">属性不加括号，方法加括号吗</d><d p="67.18000,5,25,16646914,1676364448,0,ca061618,1252194769548012288,10">删除一行文本的快捷键每个IDE工具都不一样，vscode默认是ctrl+shift+k或者ctrl+x剪切一行，具体看文件-&gt;首选项-&gt;键盘快捷方式</d><d p="16.18700,1,25,16777215,1676281141,0,dea43965,1251495932827246080,10">声音怎么这么好听</d><d p="24.24400,1,25,16777215,1676271824,0,efee3f0c,1251417782558843648,10">三毛坚持学Vue</d><d p="279.25200,1,25,16777215,1675942619,0,ea0dab1d,1248656207095429376,10">太细了</d><d p="0.00000,1,25,16777215,1675934426,0,ab4be5f,1248587480882980352,10">好嘞各位</d><d p="3.57000,1,25,16777215,1675675337,0,ee5214e9,1246414081133827584,10">小思学vue</d><d p="23.18800,1,25,16777215,1673860389,0,a0993270,1231189193980798720,10">亮亮加油！</d><d p="192.98100,1,25,16777215,1673609457,0,b124ddd5,1229084230785699584,10">还是要复写吧</d><d p="190.26300,1,25,16777215,1673405853,0,536e1874,1227376269847585280,10">那你function都可以省了</d><d p="234.80300,1,25,16777215,1673198083,0,4d4210a1,1225633369753197824,10">怎么就我一个人</d><d p="238.05100,1,25,16777215,1673095212,0,fd5b1e28,1224770425578419200,10">这个是细节</d><d p="24.28700,1,25,16777215,1672996986,0,7c6eb51d,1223946445028351744,10">小可乐学vue</d><d p="16.17100,1,25,16777215,1672996979,0,7c6eb51d,1223946390535673344,10">进度条友好</d><d p="133.81900,1,25,16777215,1672710615,0,d70b7985,1221544191612534272,10">有玉溪懂个锤子vue</d><d p="177.96600,1,25,16777215,1672641901,0,e8986528,1220967777188622080,10">function(){}</d><d p="39.45500,5,25,16776960,1672236126,0,f672f48,1217563891178200064,10">小猪佩奇学前端</d><d p="0.00000,1,25,16777215,1672232409,0,23804d8c,1217532711334656512,10">111</d><d p="237.81300,1,25,16777215,1671823207,0,4ae21d18,1214100079032636928,10">表面上是皮鞋 其实是电吹风</d><d p="211.85000,1,25,16777215,1671766054,0,e887a82,1213620639324633856,10">容易和methods混淆</d><d p="15.60000,1,25,16777215,1671556081,0,f4bab840,1211859256803309568,10">大角牛冲冲冲</d><d p="89.50900,1,25,16777215,1671060362,0,5ccdec73,1207700865281378304,10">现在都有五个人再看 你们真的是卷逼啊</d><d p="141.02100,1,25,16777215,1670770094,0,eb3d06cc,1205265920344460032,10">软件一班的别卷了 球球了</d><d p="244.31700,1,25,9033215,1670501085,0,59ce1d7,1203009313246110208,10">五人再看，晚上终于没人卷了</d><d p="10.74900,5,25,15138834,1670410714,0,b6950745,1202251223559158016,10">中国人不卷中国人</d><d p="46.89200,1,25,16777215,1670377783,0,f07dc2b1,1201974982176075008,10">大家叫vue都怎么叫</d><d p="207.04600,1,25,16777215,1670340172,0,7a6f6dfd,1201659479188781056,10">我直接method不好吗</d><d p="169.73000,1,25,16777215,1670314066,0,61db481f,1201440480844781568,10">可莉学vue</d><d p="194.58700,1,25,16777215,1670292166,0,15e68553,1201256771998827776,10">fullname ：function（）｛return｝</d><d p="33.30100,1,25,16777215,1670241163,0,2ddaa510,1200828926809802496,9">声音突然温柔</d><d p="29.71400,1,25,16777215,1670223820,0,9c7231b,1200683449497863680,9">刚开始写getter的时候就简写了，还在纳闷怎么没报错</d><d p="7.89100,1,25,16777215,1670147868,0,85ac4b8,1200046313304098304,9">好嘞老师</d><d p="63.68700,1,25,16777215,1669966699,0,3149e96,1198526561012363008,9">Ctrl +X</d><d p="57.21400,1,25,16777215,1669541145,0,4a377c52,1194956754543503104,9">卡卡米学vue</d><d p="265.70300,1,25,16777215,1669366917,0,2d2bb501,1193495222085257472,9">经典存在即合理</d><d p="217.98900,1,25,16777215,1669366868,0,2d2bb501,1193494809130733312,9">反而变复杂了</d><d p="40.28400,1,25,16777215,1669194012,0,a2099891,1192044792142412288,9">老师您真的是YYDS</d><d p="67.86100,1,25,16777215,1669179007,0,837f2a9d,1191918918378312960,9">一周直接去美团上班</d><d p="2.31800,1,25,16777215,1668996352,0,fb44f347,1190386695976310784,9">\</d><d p="39.03000,1,25,15138834,1668956103,0,32b39f32,1190049063505441024,9">小狐狸，我追着你来了。。。。</d><d p="183.14100,1,25,16777215,1668691163,0,a87ae754,1187826582791009536,9">一分钟前50人，一分钟后7人</d><d p="191.01000,1,25,16777215,1668568302,0,bb09d4d1,1186795955249367296,9">wyf才卷到这？</d><d p="124.88100,1,25,16777215,1668568264,0,bb09d4d1,1186795636582853632,9">baiyun</d><d p="64.21300,1,25,16777215,1668151680,0,e92ffc3b,1183301075433082112,9">ctrl+x 剪切一行</d><d p="78.39800,1,25,16777215,1668000110,0,d6c5b9d4,1182029611492775168,9">正经人谁写注释呀（狗头）</d><d p="71.67000,1,25,16777215,1667913500,0,19d10b78,1181303079522442496,9">东厂厂长学前端</d><d p="147.57500,1,25,16777215,1667896628,0,e10faf4b,1181161546533835776,9">由于西是谁啊</d><d p="4.33800,1,25,16777215,1667793966,0,ad5e87cd,1180300348741491456,9">细仔你在看吗</d><d p="48.17300,1,25,16777215,1667724834,0,7429cc60,1179720431209586688,9">前端强化</d><d p="250.46300,1,25,16777215,1667540258,0,c6078054,1178172095222460160,9">还是老师懂的多啊,大家要谦虚点,喊喊 6666</d><d p="120.08300,1,25,16777215,1667388347,0,247602ee,1176897773443165696,9">nono学bue</d><d p="178.76200,1,25,16646914,1667272065,0,7cdbe295,1175922330845678336,9">潘城江你个........</d><d p="2.58000,1,25,16777215,1667206066,0,fb67e71f,1175368691366295552,9">.</d><d p="71.54500,1,25,16777215,1667120048,0,18722815,1174647122977770752,9">星瞳学vue</d><d p="135.15800,1,25,16777215,1667117871,0,9f3a6751,1174628853755506176,9">机械工程专业转行来卷了</d><d p="184.62800,1,25,16777215,1667100528,0,457964ac,1174483374782399488,9">哎呀好棒</d><d p="241.70200,1,25,16777215,1667032711,0,d433d054,1173914485770203904,9">这不是和methods一样的吗</d><d p="138.32600,1,25,16777215,1666837339,0,ecb40ec8,1172275587612783360,9">注册会计师又来学前端了</d><d p="241.46100,1,25,16777215,1666622702,0,f12c7f10,1170475079608741632,9">这里就是函数</d><d p="240.57600,1,25,16777215,1666582386,0,435a4561,1170136884429902080,9">属性当做函数用</d><d p="79.73700,1,25,16776960,1666427680,0,ccf703b4,1168839114469255424,9">111</d><d p="75.79600,1,25,16777215,1666343458,0,66aad6c9,1168132613018601984,9">齐大宝贝cue第三天</d><d p="118.27300,1,25,16777215,1666106710,0,2902d70b,1166146627724291072,9">23:25</d><d p="250.93800,1,25,16777215,1666077434,0,3f544db2,1165901039959047936,9">快叫我哥们</d><d p="244.47200,1,25,16777215,1666060104,0,4e940801,1165755664627313152,9">实际上是一个属性</d><d p="185.97500,1,25,16777215,1665973102,0,a3eeb6c7,1165025837008122880,9">我为什么看着是紫色</d><d p="69.99600,1,25,16777215,1665823028,0,d1dcfec3,1163766928800527104,9">芜湖~</d><d p="247.25800,1,25,16777215,1665735959,0,7b84c3d3,1163036538792377856,9">这可就容易搞混了，还不如不简写</d><d p="134.56400,1,25,16777215,1665562172,0,bc693f30,1161578704770574592,9">论睡觉中学习</d><d p="105.11000,1,25,16777215,1665555217,0,5a7e47ad,1161520366322176512,9">fullName（）{} 就可以了</d><d p="237.99900,1,25,16777215,1665508570,0,da6e5f0c,1161129061331079424,9">这么执着给他加括号么？</d><d p="136.75600,1,25,16777215,1665507947,0,eaec7625,1161123837325459456,9">瑾溯在此每十集打卡</d><d p="33.75800,1,25,16777215,1665306258,0,d4b01d5d,1159431945025848320,9">沐萸木鱼打卡</d><d p="50.54800,1,25,16777215,1665217535,0,9e643dfe,1158687685821509888,9">小狐狸学java</d><d p="215.93300,1,25,16777215,1665061933,0,bd22cc16,1157382401572426240,9">不知道是不是版本更新 我这边简写会报错 计算属性缺少getter</d><d p="0.78500,1,25,9033215,1664874865,0,6fe5c200,1155813161803501568,9">Rem02学Vue</d><d p="201.63000,1,25,16777215,1664675705,0,973688f9,1154142480510580736,9">？？？？这到底是属性还是函数？</d><d p="113.13400,1,25,16777215,1664675635,0,973688f9,1154141895371397888,9">鱿鱼吸学vue</d><d p="162.79800,1,25,16777215,1664422344,0,8fd6f8f9,1152017137100070400,9">get也删掉</d><d p="231.08000,1,25,16777215,1664287354,0,a49fde4d,1150884760365641984,9">算代码量的</d><d p="271.26400,1,25,16777215,1664093549,0,b89c0319,1149259005185879296,9">计算属性只调用一次</d><d p="200.67900,1,25,16777215,1664080226,0,d05d0511,1149147239701324032,9">感觉vue里面很多简写它的逻辑有点乱，这次是这个规则，下次是那个规则。</d><d p="6.10100,1,25,16777215,1664000092,0,b7e69d05,1148475027969182976,9">鱿鱼系nb</d><d p="121.48600,5,25,16776960,1663642133,0,521898d,1145472256001185024,9">番茄爱西瓜每十集打卡 大家监督</d><d p="119.39900,5,25,16646914,1663642115,0,521898d,1145472101340186880,9">番茄爱西瓜每十集打卡 大家监督</d><d p="65.21900,4,25,16646914,1663590498,0,3c4fa442,1145039109270821632,9">KUN learn Vue</d><d p="22.44200,1,25,16777215,1663008806,0,691729cd,1140159518097959168,9">小橙子学VUE</d><d p="11.02300,5,25,16646914,1662977553,0,733492ca,1139897351180428288,9">我有一剑，名六千里，可搬山，断江，倒海，降妖，镇魔，敕神，摘星，摧城，开天！太监尽头谁为峰，一见总管道成空</d><d p="189.48600,1,25,16777215,1662554405,0,cbfad929,1136347725445537280,9">return出去</d><d p="15.71200,1,25,16777215,1662554266,0,cbfad929,1136346559320182272,8">vue都给封装好了</d><d p="198.80700,1,25,16777215,1662381872,0,50bbde00,1134900420880382976,8">这精简 我不要也罢</d><d p="179.11900,1,25,16777215,1662379231,0,f6db4df7,1134878263882332160,8">我觉得这样写更麻烦了</d><d p="27.80000,1,25,16777215,1662297154,0,4213e318,1134189754242628608,8">金柔美学前端</d><d p="63.00700,1,25,16777215,1661931296,0,ebde3797,1131120708395602688,8">一个周能速成吗</d><d p="232.90900,1,25,16777215,1661766054,0,1bfac4ee,1129734558862854912,8">表面函数</d><d p="201.92400,1,25,16777215,1661760268,0,e567e8ed,1129686025841505536,8">哦！明白了！！！非常感谢！！！！</d><d p="250.30200,1,25,16777215,1661455948,0,b7112854,1127133205938587136,8">谢谢老师 太细了啊</d><d p="111.06200,1,25,16777215,1661240573,0,1408437a,1125326506957128448,8">偷懒来了，简写偷懒</d><d p="134.47000,1,25,16777215,1661071445,0,6d25e97a,1123907761793427712,8">越听越有意思</d><d p="255.35000,1,25,16777215,1661007052,0,19adae52,1123367590115507200,8">一句话总结：计算属性仍是属性</d><d p="127.09500,1,25,16777215,1660963228,0,db273e55,1122999972087053824,8">是不写set的简写咋不是简写</d><d p="102.18600,1,25,16777215,1660805380,0,32af6b1e,1121675848450418944,8">老师[e]的音我都听成[ai]发音</d><d p="267.23900,1,25,16777215,1660752287,0,413870fe,1121230469820655872,8">感谢！讲的很清楚</d><d p="152.48700,1,25,16777215,1660720792,0,ebf6b8ce,1120966271190477312,8">可直接return吗</d><d p="64.59400,1,25,16777215,1660618245,0,3a67dfc5,1120106040545792768,8">ctrl + x</d><d p="97.35800,1,25,16777215,1660485557,0,c6d3b7f5,1118992972265071104,8">张震讲鬼故事</d><d p="252.42900,1,25,16777215,1660476926,0,b5960335,1118920575616805376,8">为啥不加括号</d><d p="247.56600,1,25,16777215,1660476878,0,b5960335,1118920165774494464,8">methods没有缓存</d><d p="241.64000,1,25,16777215,1660399640,0,23b0b43f,1118272252098687232,8">顶中顶</d><d p="261.80000,1,25,16777215,1660367479,0,3a109292,1118002465027975424,8">确实，我感觉简写写多了或忘记一些概念的本质</d><d p="71.72900,1,25,16777215,1660222407,0,30d38516,1116785509608499712,8">小狐狸学Vue</d><d p="205.13900,1,25,16777215,1660216230,0,c1504d68,1116733697681464832,8">7个卷王</d><d p="69.66400,1,25,16777215,1660209705,0,25cb93ed,1116678958222616320,8">胜利鹰学前端</d><d p="70.96700,1,25,16777215,1660208389,0,e211da3e,1116667919166638080,8">狗视觉学vue</d><d p="17.03000,1,25,16777215,1660205086,0,25cc046c,1116640213264016896,8">达内铭哥学VUE</d><d p="35.46300,1,25,16777215,1660061403,0,d739556c,1115434910719522816,8">3天学到这</d><d p="132.56100,1,25,16777215,1659958048,0,24bb5c4d,1114567909948131840,8">努力学习，让那些看不起我的人高攀不起！</d><d p="100.84900,1,25,16646914,1659934754,0,eec9e1f8,1114372507676559360,8">多给老子坐下</d><d p="106.06200,1,25,16777215,1659863672,0,1de42412,1113776224020454656,8">饼子打卡</d><d p="279.69000,1,25,16777215,1659838768,0,9c12d772,1113567319000391936,8">112345</d><d p="126.94700,1,25,16777215,1659771136,0,2d709748,1112999978147775232,8">我靠除夕夜竟然有102个人在听，大家都在这过除夕了吧</d><d p="71.35800,1,25,16777215,1659691319,0,b0d4cff7,1112330423003902208,8">这个老师的声音太好听了~~~</d><d p="253.95500,1,25,16777215,1659509097,0,d3a71a9b,1110801836803459840,8">BBQ</d><d p="9.15400,1,25,16777215,1659440993,0,fb2147bf,1110230533742619136,8">格陵兰岛北极圈内今日气温32.5度</d><d p="236.93000,1,25,16777215,1659431336,0,eb16215a,1110149523814233856,8">注解里面的属性也是这样的</d><d p="199.13100,1,25,16777215,1659281094,0,3b9537e,1108889205641155072,8">湖南工程职业技术学院潘婕妤在线学Vue</d><d p="187.71700,1,25,16777215,1659281061,0,3b9537e,1108888933682568192,8">湖南工程职业技术学院谭观玉在线学Vue</d><d p="8.60900,1,25,16777215,1659254304,0,88251b16,1108664477810848000,8">做一只猫打卡</d><d p="27.72200,1,25,16777215,1659199253,0,46b2af94,1108202674840694016,8">才看到12.5%。。。</d><d p="278.53200,1,25,16777215,1659059670,0,2a986ab6,1107031769338667008,8">是的，一定要跨过这个坎</d><d p="25.91600,1,25,16777215,1658850212,0,abecab6f,1105274702689065216,8">妙</d><d p="105.67500,1,25,16777215,1658636334,0,bb379977,1103480568273737984,8">对对对</d><d p="110.65500,1,25,16777215,1658562928,0,176e76e5,1102864790935762944,8">都是大学生吗？？？？</d><d p="161.24900,1,25,16777215,1658500208,0,af1cba52,1102338657139911936,8">被笑到了</d><d p="86.84400,1,25,16777215,1658500133,0,af1cba52,1102338032591443200,8">只能说设计的比较全面</d><d p="55.66100,1,25,16777215,1658500102,0,af1cba52,1102337770942153728,8">全删</d><d p="237.67000,1,25,16777215,1658484361,0,e745eb99,1102205729244316416,8">不是在凑时长把？</d><d p="203.33800,1,25,16777215,1658459770,0,779eb748,1101999444943133696,8">函数就是当做一个geteer使用de</d><d p="48.09600,5,25,16646914,1658451866,0,2cb46d38,1101933137199579648,8">小狐狸学Vue</d><d p="272.61900,1,25,16777215,1658368119,0,97921a6a,1101230619867753984,8">请你当前的你完全滴哦杀敌哦我去好多钱哦</d><d p="94.41300,1,25,16777215,1658367977,0,97921a6a,1101229423576865024,8">你好！！！！！！！！！！！！！！！！！！！！！！！！！！！！！！！！！！1</d><d p="103.25900,1,25,16777215,1658327402,0,2f16fa4c,1100889055001846016,8">是吗</d><d p="222.53800,1,25,16777215,1658301817,0,a6b10387,1100674438506221568,8">这火啊，每天都有几十个人看</d><d p="204.62100,1,25,16777215,1658299287,0,a108111d,1100653213524425984,8">前面说更长的出来挨打</d><d p="121.84700,1,25,16777215,1658220090,0,71bff991,1099988855752389120,8">好累 不能休息 一休息就不想看了</d><d p="239.40900,1,25,16777215,1658212024,0,1232753d,1099921193508813056,8">代码量有绩效的，简写是不可能简写的</d><d p="15.12100,1,25,16777215,1658162163,0,8c3bf348,1099502933135100160,8">熬到最后</d><d p="198.17800,1,25,16777215,1657987259,0,7be27fa9,1098035729659093504,8">就是在没有set的前提下，里面所有的代码默认都是get</d><d p="160.12000,1,25,16777215,1657873007,0,ba7b995a,1097077318469539072,8">直接return</d><d p="83.78600,1,25,16777215,1657781831,0,16d66e58,1096312474845580800,7">不去说书可惜了</d><d p="269.43000,1,25,16777215,1657696343,0,39b7b694,1095595351320079616,7">前端白豆腐打卡</d><d p="30.16600,1,25,16777215,1657692074,0,4e07af59,1095559544261793024,7">14  14  14</d><d p="98.49400,1,25,16777215,1657689275,0,992324be,1095536057971297536,7">好累</d><d p="36.37900,1,25,16777215,1657669557,0,b39b8012,1095370652514262784,7">后端晨哥打卡</d><d p="10.96200,1,25,16777215,1657615123,0,c29b4811,1094914025617257984,7">2022-7-12</d><d p="162.19300,1,25,16646914,1657610781,0,a7ba13f3,1094877602667049984,7">广商的同学不要卷了</d><d p="84.43900,1,25,16777215,1657546779,0,d9d5ca56,1094340716613856512,7">还剩七个人</d><d p="217.87600,5,25,16646914,1657506562,0,48823ca2,1094003349667464192,7">我一喵喵喵</d><d p="240.08900,1,25,16777215,1657443128,0,352822b8,1093471228896860160,7">问为啥不用methods的，再看一遍吧。。。</d><d p="7.95700,1,25,16777215,1657418479,0,21b88c0e,1093264463416817152,7">进度条感人</d><d p="7.95700,1,25,16777215,1657418475,0,21b88c0e,1093264424224994048,7">进度条感人</d><d p="116.15300,1,25,16777215,1657262266,0,af4baf,1091954049357728512,7">你要相信我卷你们是对你们好</d><d p="57.40400,4,25,16646914,1657072252,0,38ae246b,1090360099022631168,7">在电线杆上多嘴~</d><d p="0.00000,1,25,16777215,1657036468,0,dd2a388,1090059917701814272,7">太细了</d><d p="0.00000,1,25,16777215,1657036431,0,dd2a388,1090059611182103296,7">666</d><d p="281.25000,1,25,16777215,1657027461,0,4c80a6ff,1089984365267784192,7">随意定义</d><d p="52.57100,1,25,16777215,1656991089,0,75985973,1089679252745571584,7">常熟·阿诺学前端</d><d p="228.97100,1,25,16777215,1656920266,0,fe5f5732,1089085148072294656,7">好嘞</d><d p="94.73900,1,25,16777215,1656839115,0,6cac86d5,1088404405964848384,7">保佑</d><d p="39.03300,1,25,16777215,1656641760,0,ea02079d,1086748870194668544,7">总共168集，我猜看到20集，我麻了</d><d p="67.83700,1,25,16646914,1656505373,0,47f7cf23,1085604773400605184,7">CTRl + W 删除页面</d><d p="175.38000,1,25,16777215,1656433103,0,9ec21317,1084998528993888000,7">面试背题吧</d><d p="114.17500,1,25,16777215,1656240605,0,daa8fd54,1083383737414164992,7">算不算留后门的方法</d><d p="132.99700,1,25,16777215,1656161033,0,fc3e42f8,1082716235071908864,7">我giao 信管的家人你们好！</d><d p="84.67700,1,25,16777215,1656149858,0,1c775a5f,1082622492947937792,7">小狐狸学Vue</d><d p="144.25400,1,25,16777215,1656146738,0,a47103dd,1082596323728861696,7">只读不改计算属性，就用简写 不用set</d><d p="156.29100,1,25,16777215,1655985560,0,1ded6eda,1081244264316310016,7">哈哈</d><d p="47.97100,1,25,16777215,1655865306,0,db495c18,1080235500205270784,7">老师的声音太好听了</d><d p="49.81300,1,25,16777215,1655814576,0,de6e50e2,1079809945408640256,7">范鑫别卷了</d><d p="271.82800,1,25,16777215,1655799014,0,cf81b954,1079679400674337024,7">注意不要用剪头函数哦，狗头</d><d p="264.32000,1,25,16777215,1655685808,0,423e099,1078729758457626368,7">数据</d><d p="91.77000,1,25,6830715,1655619500,0,dcd3a487,1078173528802711296,7">冲冲冲冲</d><d p="228.97900,1,25,16777215,1655609280,0,ad256068,1078087794947187200,7">千行代码BUG</d><d p="147.88700,1,25,16777215,1655609215,0,ad256068,1078087250769758464,7">还有8个老哥</d><d p="17.31200,1,25,16777215,1655576207,0,9b078c78,1077810360662229248,7">进度条好评</d><d p="59.29400,1,25,16777215,1655391914,0,71957c81,1076264396814039552,7">智能学vue</d><d p="86.58900,1,25,16777215,1655227865,0,59e2c30c,1074888253624187648,7">第二个人你好</d><d p="48.07100,1,25,16777215,1655192047,0,4457dd6d,1074587791377097728,7">吴签学vue</d><d p="12.01500,1,25,16777215,1654929173,0,ced20f1d,1072382645075245056,7">大伟哥学Vue</d><d p="24.67300,1,25,16777215,1654755075,0,690bcc8a,1070922205183342592,7">经典白学</d><d p="242.77300,1,25,16777215,1654587166,0,831d8cbe,1069513686445598720,7">代码量绩效</d><d p="18.31000,1,25,16777215,1654579838,0,eaebe482,1069452210255011840,7">argument，ents</d><d p="132.55400,1,25,16777215,1654565620,0,f538b831,1069332941580040960,7">张嘉韵学Vue</d><d p="137.33800,1,25,16777215,1654516435,0,15f68477,1068920350538155264,7">5个人gogogo</d><d p="113.52600,1,25,16777215,1654494407,0,73dfd800,1068735564905266688,7">一凡   加油</d><d p="185.25700,1,25,16777215,1654398864,0,16119213,1067934089019029248,7">红</d><d p="32.08000,1,25,16777215,1654346328,0,67344b3e,1067493391257936128,7">跳转不了的    component:()=&gt; import('../views/home/index.vue')</d><d p="272.62400,1,25,16777215,1654334060,0,bc0fb4b,1067390481367027712,7">妙啊</d><d p="25.23300,5,25,16776960,1654069432,0,ae4daa33,1065170615255785728,7">韬子哥打卡</d><d p="26.87900,1,25,16777215,1654055946,0,c613e28,1065057485431347968,7">1.25是我最后的倔强</d><d p="26.77400,1,25,16777215,1653729926,0,1f485306,1062322634554921472,7">经典白学</d><d p="29.65200,1,25,16777215,1653620349,0,9247b769,1061403439805948160,7">小洛学Vue</d><d p="271.97800,1,25,16777215,1653611588,0,801aa3ee,1061329947009860864,7">没脑子就别听了，还在问和methods区别</d><d p="243.86400,1,25,16777215,1653501999,0,38f21c54,1060410642042881792,7">计算属性，写成函数，实际为属性，必须return</d><d p="10.01800,1,25,16777215,1653478630,0,8631a14a,1060214609811779072,7">奥里给！</d><d p="247.55000,1,25,16777215,1653395401,0,cdcdbb07,1059516434490704896,7">代理了</d><d p="8.10700,1,25,16777215,1653307911,0,4617981,1058782512190401792,7">妙蛙种子学vue</d><d p="232.62700,1,25,16777215,1653295565,0,6ff6f5ae,1058678948432445696,7">methods 中是函数 computed中是不带括号</d><d p="103.57000,5,25,16777215,1653197510,0,48482318,1057856407283525120,7">计科五班的刘洋别卷了</d><d p="159.42700,1,25,16777215,1653038172,0,2a8f1d48,1056519781819215360,7">写成函数的形式</d><d p="215.60400,1,25,16777215,1653014605,0,e5fc93c4,1056322089381892096,6">ES6</d><d p="16.68300,1,25,16777215,1652921584,0,729e6228,1055541767602136832,6">时长友好</d><d p="10.20300,1,25,16777215,1652856331,0,b6ef3ec,1054994388129816576,6">+</d><d p="32.71200,1,25,16777215,1652854973,0,f576fe49,1054982994462287616,6">大灰狼学Vue</d><d p="9.87100,1,25,16777215,1652854830,0,f576fe49,1054981799840828160,6">小灰狼学前端</d><d p="83.94900,1,25,16777215,1652705829,0,f2e4299e,1053731887316543232,6">王鹏鹏学前端</d><d p="79.76800,1,25,16777215,1652705449,0,118f11fc,1053728695501480960,6">666</d><d p="63.27900,1,25,16777215,1652627722,0,19a0c7c5,1053076677128866560,6">删除整行ctrl+k</d><d p="19.57800,5,25,15138834,1652343709,0,eec38bca,1050694201148225024,6">小狐狸学vue </d><d p="225.64200,1,25,16777215,1652254158,0,c24527f8,1049942995111002880,6">代码量算绩效那个还要人吗</d><d p="43.96700,1,25,16777215,1652152969,0,71c1b46c,1049094160147543040,6">甩棍学vue</d><d p="84.97100,1,25,16777215,1652145570,0,ecb6d9d5,1049032095378336768,6">这比听书有意思多了</d><d p="235.73300,1,25,16777215,1652073466,0,2e7ef664,1048427241861672192,6">hhhhhhhh</d><d p="145.61100,1,25,16777215,1651995334,0,ac2ab4d0,1047771821514029312,6">但是面试需要用呢</d><d p="241.44000,1,25,16777215,1651919155,0,5e462280,1047132783312447744,6">作用是以后看代码的时候绕死自己？</d><d p="148.45200,1,25,16777215,1651907135,0,7240f8c1,1047031957512464640,6">3</d><d p="242.08000,1,25,16777215,1651855344,0,33378eeb,1046597496782151936,6">可读性太差了，还是原来的格式好点。。。</d><d p="158.03100,1,25,16777215,1651597379,0,af9a722c,1044433530576224000,6">《简写》</d><d p="106.38700,1,25,16777215,1651505098,0,5829f8e2,1043659425225066752,6">实时的</d><d p="67.68600,1,25,16777215,1651505052,0,5829f8e2,1043659038610502400,6">在线扣个六六六</d><d p="227.90100,1,25,16777215,1651499110,0,536f161a,1043609191337620736,6">methods</d><d p="252.29700,1,25,16777215,1651208143,0,4adfece5,1041168388686183424,6">methods</d><d p="250.86000,1,25,16777215,1651139166,0,99f1cb38,1040589765902075904,6">类似py的属性方法</d><d p="11.72700,1,25,9033215,1651138503,0,9069efae,1040584201545538048,6">苏啾啾学前端，冲冲冲！！！</d><d p="235.56600,1,25,16777215,1650976290,0,18198a49,1039223462499397376,6">lambda的感觉了</d><d p="248.53700,1,25,16776960,1650900192,0,b6277f74,1038585107038157824,6">别说没用，项目里用get，不用set时，都是这么写的，习惯吧</d><d p="64.85800,1,25,16777215,1650627251,0,c17156a,1036295512904555008,6">你说这一切</d><d p="52.91400,1,25,16777215,1650527334,0,151fae84,1035457341967140864,6">所以说程序员就不要写注释</d><d p="61.59600,4,25,52480,1650523421,0,520c32d0,1035424520615605248,6">在电线杆上多嘴</d><d p="15.51600,1,25,16777215,1650445226,0,cc386a8c,1034768575669305856,6">经历了魔抓</d><d p="12.76300,1,25,16777215,1650372522,0,8cdaaf58,1034158686009903616,6">尤雨溪学vue</d><d p="254.67100,1,25,16777215,1650362348,0,88ff2e8e,1034073339095733760,6">精简得面目全非了</d><d p="243.08400,1,25,16777215,1650269225,0,b18a74ee,1033292174218969088,6">我觉得新手还是第一种写法好理解</d><d p="214.34100,1,25,16777215,1650113067,0,b8e986f,1031982218102511104,6">算绩效那不多整点</d><d p="121.19800,1,25,16777215,1650106923,0,4feea27e,1031930679232936960,6">这是不写，不是简写</d><d p="21.73500,1,25,16777215,1650026317,0,bf0e8194,1031254513656347136,6">小橙子学前端</d><d p="16.65700,1,25,16777215,1650010920,0,8d96ecec,1031125354745452544,6">小老虎学vue</d><d p="11.28000,1,25,16777215,1650010844,0,1764a5b8,1031124717328694784,6">邱邱学vue</d><d p="178.70300,1,25,16777215,1649991343,0,915fd69,1030961129138184192,6">如果只是会用那么35岁退休的就是你，不准备时时刻刻了解底层了解原理，这种只是单纯的cv工程师罢了</d><d p="233.92300,1,25,16777215,1649946544,0,48356055,1030585328735480320,6">代码量也很重要呀</d><d p="2.55300,1,25,16777215,1649935314,0,9d0b9a00,1030491119315827200,6">加油！！！</d><d p="273.19600,1,25,16777215,1649744862,0,5478506e,1028893492253838336,6">duck不必</d><d p="246.68500,1,25,16777215,1649744849,0,5478506e,1028893383780978176,6">大可不必</d><d p="251.41400,1,25,16777215,1649521296,0,b452ff03,1027018087595344896,6">简写可读性就差了</d><d p="213.13900,1,25,16777215,1649521252,0,b452ff03,1027017716667653120,6">好像也没减少多少</d><d p="211.90200,1,25,16777215,1649498291,0,17d58af1,1026825105915126784,6">它已经变成了函数的形状了</d><d p="126.98800,1,25,16777215,1649476509,0,3e528859,1026642386966560256,6">由于西他懂个锤子vue</d><d p="7.15100,1,25,16777215,1649436202,0,bb3fa673,1026304267478115840,6">老师屏幕标注的软件叫什么呀</d><d p="196.72400,1,25,16777215,1649403140,0,4bc04717,1026026920124550144,6">讲的太细太细了</d><d p="206.00300,1,25,16777215,1649383754,0,dcaf210a,1025864298276074496,6">一个属性 活生生变成一个方法的样子</d><d p="55.03800,1,25,16777215,1649255236,0,8b2c536d,1024786215381024768,6">现在怎么只有12个人</d><d p="40.05400,1,25,16777215,1649255221,0,8b2c536d,1024786089694746624,6">小猛男来此学习</d><d p="12.93200,1,25,16777215,1649207786,0,95454659,1024388171099889664,6">森森老婆学Vue</d><d p="220.44000,1,25,16777215,1649143094,0,a86faf7d,1023845500941664256,6">那为什么不直接用methods呢？</d><d p="16.84300,1,25,9033215,1649038556,0,530e57dd,1022968568351889920,6">第二天打卡</d><d p="177.40800,1,25,16777215,1648824061,0,caf422f0,1021169252335552512,6">醉了，我就说以前用的时候是这样用的，现在咋不一样了</d><d p="206.79200,1,25,16777215,1648802570,0,f551f4f1,1020988977668588032,6">代码量算绩效可还行</d><d p="281.00000,1,25,16777215,1648747319,0,6272b70d,1020525496389383168,6">只读就用简写，</d><d p="34.26000,1,25,16777215,1648636961,0,9537bf38,1019599746656156672,6">鸡哥打卡</d><d p="218.86000,1,25,16777215,1648633193,0,f7b99e7a,1019568138146225664,6">着好熟悉啊</d><d p="14.42700,1,25,16777215,1648608736,0,43290299,1019362976332941824,5">赖奕博学习Vue</d><d p="133.79200,1,25,16777215,1648569211,0,cbabb38d,1019031422004340736,5">23点55了，还有9个人在卷</d><d p="150.08000,1,25,16777215,1648559122,0,5e7e8ddd,1018946784279494656,5">卷起来</d><d p="137.02100,1,25,16777215,1648559113,0,5e7e8ddd,1018946711223454208,5">13人正在卷</d><d p="23.19000,1,25,16777215,1648539150,0,a43e6c04,1018779245289228288,5">轩辕电视机前来学习</d><d p="275.57000,1,25,16777215,1648448813,0,c3766eb0,1018021445085092352,5">fullname:function</d><d p="48.41800,1,25,16777215,1648442906,0,a9c41696,1017971893644362240,5">东星斑学前端</d><d p="43.76000,1,25,16777215,1648375679,0,fc9d7e03,1017407957962360832,5">二流子报到</d><d p="44.12400,1,25,16777215,1648282264,0,dcedd41b,1016624329460459520,5">污渍棋前来学vue</d><d p="44.17000,1,25,16777215,1648224380,0,b5c80b08,1016138766387158528,5">兄弟们冲冲冲</d><d p="279.12700,1,25,16777215,1648219247,0,d6db6c29,1016095711479165440,5">注意哦</d><d p="245.02200,1,25,16777215,1648219210,0,d6db6c29,1016095393945118720,5">太细了，恍然大悟</d><d p="105.22300,1,25,16777215,1648219070,0,d6db6c29,1016094222190893056,5">别卷了</d><d p="34.85300,1,25,16777215,1648125890,0,c6e112c3,1015312576504060416,5">冲冲冲</d><d p="111.03600,1,25,16777215,1648041911,0,ad747c1f,1014608106782689280,5">信息管理与信息系统1班的同学卷起来</d><d p="81.80200,1,25,16777215,1648041821,0,ad747c1f,1014607355423410688,5">小陈入职狂补知识</d><d p="122.90000,1,25,16777215,1648028625,0,5e5851e3,1014496658010389504,5">尤雨溪懂个锤子vue</d><d p="67.32700,1,25,16777215,1648022129,0,1d26470c,1014442162693111808,5">声音好像动物世界</d><d p="73.47900,1,25,16777215,1648001719,0,7da0a5d1,1014270953821179904,5">我刘东昌一定要卷死你们</d><d p="17.58600,1,25,16646914,1647960925,0,86d60644,1013928749063908864,5">小瓜皮学vue</d><d p="42.32800,1,25,16777215,1647952261,0,5d74d885,1013856070826811392,5">2022-3-22</d><d p="41.92400,1,25,16777215,1647947433,0,cccdba79,1013815568287109120,5">视频的代码有没有渠道下载呀</d><d p="194.21700,1,25,16777215,1647853049,0,95e02e84,1013023818522159104,5">不早说 doge</d><d p="73.49000,1,25,16777215,1647849953,0,6de2cac9,1012997849010754048,5">求怕累</d><d p="27.14600,1,25,16777215,1647849752,0,3f11fc3e,1012996163714079232,5">饿死了，早知道不学前端了</d><d p="70.73300,1,25,16777215,1647784387,0,4eb821ae,1012447836127900160,5">丢雷</d><d p="261.36300,1,25,16777215,1647752355,0,76ec9369,1012179135181076992,5">那和直接在methods里面写有什么区别</d><d p="216.02100,1,25,16777215,1647752316,0,76ec9369,1012178811153824256,5">我选择直接用method</d><d p="20.05000,1,25,16777215,1647701165,0,6faf9ed9,1011749717891185152,5">53人</d><d p="203.36300,1,25,16777215,1647671625,0,27ff19a5,1011501924719351296,5">function 可以去掉吗</d><d p="25.77300,1,25,16777215,1647521364,0,edbcc891,1010241442003597312,5">m:) 3.17</d><d p="6.28600,1,25,16777215,1647507964,0,871f7f4f,1010129033322612736,5">2022-3-17</d><d p="79.72300,1,25,16776960,1647496284,0,ba40c757,1010031051638294016,5">来啦</d><d p="226.12000,1,25,16777215,1647446185,0,7cfbc058,1009610797418259968,5">知道啦知道啦知道啦</d><d p="35.57100,1,25,16777215,1647412503,0,fbe93755,1009328250612139520,5">彦祖学前端</d><d p="180.39300,1,25,16777215,1647395980,0,77214497,1009189643436047360,5">每次修改代码必然报错，不是标点捣乱就是大括号捣乱</d><d p="155.59100,1,25,16777215,1647395700,0,77214497,1009187291580608512,5">实际工作中，只要会用就行了，能明白底层的时候你已经是大佬级了</d><d p="73.33600,1,25,16777215,1647395617,0,77214497,1009186601491944960,5">老咸鱼学前端，冲冲冲</d><d p="17.06800,4,25,16646914,1647352380,0,3d99782a,1008823901830231040,5">研棋-22-3-15</d><d p="20.59100,1,25,16777215,1647262107,0,6cc89ac8,1008066639880718848,5">大苹果学习VUE</d><d p="107.23400,1,25,16646914,1647241334,0,c61793cb,1007892383016284672,5">信息管理与信息系统2班的同学别卷了</d><d p="32.55800,1,25,16777215,1647149068,0,361bca37,1007118397193920000,5">壹城学vue</d><d p="11.16900,1,25,14811775,1647070217,0,240fcf82,1006456947299396096,5">pink公主冲冲冲</d><d p="199.64900,1,25,16777215,1647058433,0,b25a23a5,1006358094449661952,5">说白了就是对象格式变成了函数格式</d><d p="135.10700,1,25,16777215,1646982397,0,5cdfcf7d,1005720255248685568,5">我想睡觉</d><d p="102.96300,1,25,16777215,1646982364,0,5cdfcf7d,1005719982056950272,5">就是干</d><d p="94.86400,1,25,16777215,1646982353,0,5cdfcf7d,1005719888674827776,5">爱你就是哎</d><d p="84.23300,1,25,16777215,1646982335,0,5cdfcf7d,1005719740976609280,5">爱你么么么哒</d><d p="74.67000,1,25,16777215,1646982326,0,5cdfcf7d,1005719660831934464,5">12个人在卷</d><d p="0.00100,1,25,16777215,1646915787,0,1d51d03d,1005161496117900800,5">20/168 波波</d><d p="278.86400,1,25,16777215,1646876255,0,732615e7,1004829873463835136,5">有啥区别上一节白听了？</d><d p="35.93500,1,25,16777215,1646876065,0,732615e7,1004828284359565312,5">四棱子到此一游</d><d p="103.17300,1,25,16777215,1646843959,0,b2957572,1004558954518379008,5">这个老师讲课算是我听过最舒服的了</d><d p="142.99600,1,25,16777215,1646811331,0,3b1dfd4,1004285254346945536,5">裆下很忧郁啊</d><d p="6.79800,1,25,16777215,1646809676,0,6d1e8e8b,1004271370361701888,5">莹莹打卡</d><d p="88.38700,1,25,16777215,1646788623,0,ce1e5707,1004094760325063168,5">李阳冰学vue</d><d p="257.19800,1,25,16777215,1646751844,0,790b71b5,1003786239729502720,5">计算属性可以缓存，以后调用直接取结果，大量使用该属性可以节省资源</d><d p="81.38700,1,25,16777215,1646726829,0,2830a5d,1003576398624968192,5">尤雨溪是谁啊？一听就不懂VUE</d><d p="272.97100,1,25,16777215,1646576647,0,cfc08de4,1002316578240558080,5">还可以简写，把function去掉</d><d p="189.42900,1,25,16777215,1646571242,0,bf260350,1002271239097939456,5">本来学习是件挺严肃的事情，被你们发的弹幕整的走神了</d><d p="19.37700,1,25,16777215,1646571072,0,bf260350,1002269812740643840,4">加油，卷起来</d><d p="11.88900,1,25,16777215,1646570100,0,a958a3be,1002261663434496512,4">我丢</d><d p="215.41700,1,25,16777215,1646506221,0,2e4daaf9,1001725807879838720,4">那我要两个function呢</d><d p="210.91000,1,25,16777215,1646452711,0,95073e76,1001276932954118144,4">？？？？？？？？？？？</d><d p="19.33900,1,25,16646914,1646290848,0,ce571cd0,999919125809843712,4">小马学Vue</d><d p="272.03600,1,25,16777215,1646275907,0,1f948cbe,999793791323956736,4">Nice</d><d p="123.69100,1,25,16777215,1646221145,0,5e5851e3,999334417543559680,4">尤雨溪懂个锤子vue</d><d p="56.81000,4,25,52480,1646120652,0,dfc3b489,998491414734108160,4">窗外～的麻雀</d><d p="245.29600,1,25,16646914,1646052324,0,868075d,997918242644729856,4">如果你尝试在页面修改的话，也能修改</d><d p="244.56500,1,25,16777215,1645957755,0,b0b5ff3f,997124941759602688,4">这样写好像还不如写get</d><d p="259.08200,1,25,16777215,1645942145,0,e82cf862,996993995858190336,4">说跟method有什么区别的，前面的看过了吗？</d><d p="71.32200,1,25,16777215,1645856730,0,111bbdd7,996277479648886784,4">进度条 女少啊</d><d p="24.79000,1,25,16777215,1645780275,0,8af3fe46,995636124487311360,4">恒哥来了</d><d p="143.27700,1,25,16777215,1645706091,0,86f60c0c,995013824373956608,4">这是我见过人最少的一次 8个</d><d p="168.77100,1,25,16777215,1645605752,0,80e063a0,994172126745673728,4">2022-02-23-留念</d><d p="72.69100,1,25,16777215,1645605656,0,80e063a0,994171320987525120,4">小张学前端</d><d p="145.60900,1,25,16777215,1645578621,0,4292ca8e,993944534252888064,4">return</d><d p="29.66000,1,25,16777215,1645435426,0,c233daed,992743321337249792,4">我靠天才小熊猫！</d><d p="123.96100,1,25,16777215,1645193980,0,12cf8c85,990717932862619648,4">告诉你们·实际工作中·你不用这么明白···会用就行·····</d><d p="17.68000,1,25,16777215,1644983977,0,9629d0fe,988956293787967488,4">进度条感人</d><d p="264.28200,1,25,16777215,1644916488,0,cb8614cf,988390161833762816,4">常问面试题methods和conputed的区别</d><d p="278.51500,1,25,16777215,1644854205,0,8d2fc8b9,987867692814614528,4">我可以在methods中写一个方法，data中写一个fullname,在方法中重新赋值，模型中在调用，不也可以打到效果。</d><d p="6.03400,1,25,16777215,1644845156,0,7ddd5052,987791781744017408,4">小遥</d><d p="236.67300,1,25,16777215,1644831831,0,ac889c14,987680003579764736,4">太细了</d><d p="85.84700,1,25,16777215,1644588464,0,d4469fac,985638491584069632,4">我也觉得</d><d p="15.06500,1,25,16777215,1644564415,0,85b9a50f,985436754550939648,4">我将带头冲锋</d><d p="89.37600,1,25,16777215,1644417431,0,23fe78b6,984203764565106688,4">这节课老师嗓音温柔了些</d><d p="216.26200,1,25,16777215,1644415545,0,f6bbf077,984187940022935552,4">这是什么提示插件啊</d><d p="273.56300,1,25,16777215,1644328215,0,5a47af58,983455368244871168,4">说和methods一样的可以重看了，不然以后踩坑</d><d p="72.42000,1,25,16777215,1644323619,0,90ba91ca,983416810620616704,4">鱿鱼须不会vue</d><d p="151.05600,1,25,16777215,1644047380,0,7336c75a,981099555433619456,4">如果是对象的属性，怎么用计算属性</d><d p="263.22800,1,25,16777215,1643970560,0,fd6ac5,980455138895847424,4">传参呢</d><d p="50.84100,1,25,16777215,1643895895,0,98c43fe5,979828803021529088,4">李阳勇学前端</d><d p="9.92900,5,25,16646914,1643789218,0,ad1c6f8,978933934262444032,4">2倍速已经不能满足我了</d><d p="118.79100,1,25,16777215,1643692152,0,36908fcf,978119680099516416,4">新年快乐</d><d p="256.43500,1,25,16777215,1643624599,0,c7f69953,977553009024925696,4">简写不能写逻辑？</d><d p="246.05600,1,25,16777215,1643480089,0,b71de5c5,976340769475125248,4">服了，不是说了计算属性有缓存，效率高吗，你听哪去了</d><d p="139.18000,1,25,16777215,1643356600,0,c5d9cc2,975304865576542208,4">一键三连</d><d p="185.49900,1,25,16777215,1643356197,0,e2cda6a7,975301489023213568,4">加了vue插件直接提示的这种</d><d p="59.28300,1,25,16777215,1643267432,0,60c82b31,974556870111485952,4">删掉一行的快捷键是啥</d><d p="245.27500,1,25,16777215,1643248470,0,eac6040f,974397812742348800,4">写在methods里面每次解析模板都会调用，但是计算属性有缓存机制，所以计算属性的效率更好。</d><d p="127.28900,1,25,11392418,1643178756,0,770a3c22,973813005524287488,4">江东孤狼冲冲冲</d><d p="3.44800,1,25,16777215,1642938987,0,6d5c8b53,971801676966633472,4">天不负你剑九黄，世子端酒问上苍</d><d p="275.10500,1,25,16777215,1642586407,0,f7564419,968844019879723008,4">靠子归隐了</d><d p="132.23600,1,25,16777215,1642586289,0,f7564419,968843035052556288,4">一集比一集人数傻</d><d p="276.10200,1,25,16777215,1642575074,0,bac1fb61,968748951350902784,4">注意噢</d><d p="9.91500,1,25,16777215,1642573701,0,bac1fb61,968737437699743744,4">杰尼斯学Vue</d><d p="95.46500,1,25,16777215,1642340143,0,13c1688e,966778212129898496,4">弹幕是实时的吗</d><d p="76.91300,1,25,16777215,1642340122,0,13c1688e,966778032156467200,4">刚刚的40+去哪了</d><d p="132.15400,1,25,16777215,1642306198,0,9e4813cd,966493456239001600,4">发个忧伤的弹幕见证当下</d><d p="273.74600,1,25,16777215,1641959880,0,d0e49ab4,963588331607351296,4">效率高</d><d p="102.35200,1,25,16777215,1641895815,0,ac86441b,963050918196633600,4">小马哥冲啊</d><d p="13.06000,1,25,16777215,1641733881,0,a327dd6f,961692518543474688,4">好累各位！！！</d><d p="186.43400,1,25,16777215,1641642660,0,9f028840,960927298881232896,4">你写get还多一对小括号一对大括号呢</d><d p="115.93800,1,25,16777215,1641623432,0,f855760b,960766000306749440,4">一集比一集的人数少</d><d p="222.91900,1,25,16777215,1641524517,0,fd4a20c7,959936240556081152,4">实际代码中就是简写，没看到有多少用get的</d><d p="193.09900,1,25,16777215,1641457727,0,fa135707,959375969320017920,4">15</d><d p="118.64300,1,25,16777215,1641448615,0,63c27d42,959299529620332544,4">尤雨溪学习vue第一天</d><d p="52.19700,1,25,16777215,1641437739,0,6d4750a6,959208298959249408,4">靠嫩娘</d><d p="7.37100,1,25,16777215,1641396906,0,b5f18725,958865765698535424,4">进度条感人</d><d p="10.79500,1,25,16777215,1641375081,0,6a956984,958682680457797632,4">来个 3.0x 速度</d><d p="58.11800,1,25,16777215,1641307941,0,129a100a,958119468445999104,3">第一天就看到这集吧 Mark</d><d p="140.07100,1,25,14811775,1641289972,0,38f46b29,957968739487121408,3">陈卷王20集了，歇一歇吧</d><d p="161.24400,1,25,16777215,1641289896,0,5bcbce46,957968098401828864,3">做成函数 不要set</d><d p="240.22400,1,25,16777215,1641215666,0,e0102dd,957345416635375616,3">一渺</d><d p="213.69400,1,25,16777215,1641052715,0,b2461b86,955978478632132608,3">再看的兄弟们好</d><d p="38.58800,1,25,16777215,1641035637,0,a6a3c458,955835221067161600,3">2022-1-1</d><d p="2.15300,1,25,16777215,1640780994,0,11b899a6,59606195207618048,3">杰尼龟学vue</d><d p="117.98100,1,25,16777215,1640741701,0,3154162b,59585593913646080,3">乾龙学习Vue</d><d p="144.73300,1,25,16777215,1640657223,0,34bc6465,59541303440738816,3">我喜欢熊小姐 打卡二十集</d><d p="90.82500,1,25,9033215,1640620310,0,2806a98a,59521950416172032,3">老师 666</d><d p="68.69700,1,25,16777215,1640616284,0,e901adb4,59519839485414912,3">《靠家军集合》</d><d p="10.02500,1,25,16777215,1640316874,0,cb42da04,59362862288258560,3">靠子学vue，邦邦就是两拳，求怕累</d><d p="209.06300,1,25,16777215,1640142764,0,d8ca2767,59271578624026624,3">算绩效草了哈哈哈</d><d p="239.66300,1,25,16777215,1640049506,0,c672902a,59222684811682304,3">恍然大悟</d><d p="31.10300,1,25,16777215,1639843812,0,b2782c97,59114841696891904,3">大卡</d><d p="39.53000,1,25,16777215,1639814284,0,faf918b6,59099360301137920,3">棒棒给你两拳</d><d p="45.50200,1,25,16777215,1639814278,0,faf918b6,59099357384803328,3">棒棒给你两拳</d><d p="37.37300,1,25,16777215,1639814272,0,faf918b6,59099353980965888,3">棒棒给你两拳</d><d p="65.09300,1,25,16777215,1639727233,0,51f98fd8,59053720515913216,3">一下子人就少了</d><d p="184.31000,1,25,16777215,1639726008,0,45a3b678,59053078501036032,3">12个人</d><d p="169.59500,1,25,16777215,1639725993,0,45a3b678,59053070832644096,3">12ger</d><d p="206.52000,1,25,16777215,1639661946,0,2cbd7373,59019491770753024,3">计算属性插值语法不需要()</d><d p="134.43400,1,25,10546688,1639465088,0,412d8162,58916281149632512,3">打卡</d><d p="215.67200,1,25,16777215,1639407011,0,275d3876,58885832026688000,3">我感觉还是写getter把  好读一点</d><d p="94.86600,1,25,16777215,1639406806,0,275d3876,58885724674509824,3">计科5班的同学别卷了</d><d p="97.53200,1,25,16777215,1639316773,0,6fc4e422,58838521703861760,3">冲冲冲</d><d p="248.83600,1,25,16777215,1639224640,0,fba30cad,58790217125713920,3">那和直接在methods里面写有什么区别</d><d p="241.98600,1,25,16777215,1639224634,0,fba30cad,58790214277138432,3">那和直接在methods里面写有什么区别？</d><d p="251.10600,1,25,16777215,1639127336,0,6c36cf59,58739201693422592,3">求怕累</d><d p="200.96900,1,25,16777215,1638967259,0,ca110e6d,58655275406590976,3">那上面调用还是fullName还是fullName()</d><d p="103.91100,1,25,16777215,1638954972,0,296a9976,58648833484024320,3">冲冲冲，BREEZE</d><d p="164.27600,1,25,16777215,1638953035,0,97faa7be,58647817841662464,3">讲个笑话</d><d p="17.67200,1,25,16777215,1638945400,0,148eee74,58643815170508288,3">尤雨溪学vue</d><d p="64.62900,1,25,16777215,1638939726,0,e8758f86,58640840011332096,3">小志学前端回头复习 21.12.08</d><d p="35.33800,1,25,16777215,1638687445,0,b1c447fa,58508572469376512,3">试试试试</d><d p="19.15700,1,25,41194,1638619826,0,7871f88d,58473120657544192,3">前端吴磊打卡</d><d p="249.62600,1,25,16777215,1638604610,0,f38efa5,58465142971363328,3">觉着完整写法不容易混淆</d><d p="277.78700,1,25,16776960,1638494140,0,b75b525b,58407225068700160,3">兄弟你搞错了</d><d p="109.39000,1,25,16776960,1638493972,0,b75b525b,58407136784537600,3">我在看简写了</d><d p="69.70400,1,25,16776960,1638493932,0,b75b525b,58407115983381504,3">切</d><d p="54.56000,1,25,16777215,1638283249,0,ff39c299,58296657325073408,3">迪迪学vue</d><d p="60.86500,1,25,16777215,1638269483,0,3d7e055b,58289439879297024,3">高飞翔别卷了,中国人不卷中国人</d><d p="247.93400,1,25,16777215,1638255163,0,3e5c4923,58281932324429824,3">funllname = get()，没毛病</d><d p="24.05100,1,25,16777215,1638192819,0,7ecc2bcd,58249245936735744,3">好嘞各位</d><d p="15.67000,1,25,16777215,1638106900,0,2541fea5,58204199459781120,3">还以为老师忘了</d><d p="204.65500,1,25,16777215,1637992776,0,7d758131,58144365515923968,3">fullName(){}</d><d p="3.46400,1,25,16777215,1637984857,0,910e38c7,58140213679639040,3">中国人不卷中国人</d><d p="194.12800,1,25,16777215,1637927603,0,55f8c56d,58110196349668352,3">函数里直接return</d><d p="146.34400,1,25,16777215,1637927555,0,55f8c56d,58110171296618496,3">计算属性里面直接写函数就行</d><d p="87.96200,1,25,16777215,1637927496,0,55f8c56d,58110140069000704,3">本来就是计算结果，再去修改一遍，图啥呢</d><d p="200.57800,1,25,16777215,1637925641,0,50c16167,58109167626928640,3">一下就舒服了</d><d p="200.57800,1,25,16777215,1637925634,0,50c16167,58109164047117824,3">卧槽</d><d p="50.70100,1,25,16777215,1637911072,0,d5f00fa2,58101529098561024,3">开始卷吧</d><d p="5.55500,1,25,16777215,1637911010,0,d5f00fa2,58101496840257024,3">学不会</d><d p="207.47400,1,25,16777215,1637744963,0,379114fa,58014440198801408,3">要不你写个框架？？你想咋写咋写</d><d p="9.18300,1,25,16740868,1637735500,0,678c8eb5,58009479196391424,3">255打卡</d><d p="50.10400,1,25,16777215,1637719746,0,f6eba453,58001219276092928,3">广州靓仔前来打卡</d><d p="26.61700,1,25,16777215,1637649103,0,d20039dc,57964182374611456,3">9个人内卷小狂人</d><d p="70.02300,1,25,16777215,1637583016,0,a8182af6,57929533587779584,3">time（）</d><d p="171.34000,1,25,16776960,1637495536,0,4a622ea,57883668755351040,3">fullName(){return 张三}</d><d p="216.59200,1,25,16777215,1637378580,0,e1a1229f,57822350175042560,2">.</d><d p="36.27500,1,25,16777215,1637374902,0,6ef5e15e,57820421714395136,2">紫色闪电打卡</d><d p="86.70500,1,25,16777215,1637329434,0,2953d412,57796583531116032,2">每节一冲！！！</d><d p="228.08100,1,25,16777215,1637324963,0,3105b9c6,57794239471636480,2">如果只需要读的话，为啥不简写</d><d p="192.78600,1,25,16777215,1637324921,0,3105b9c6,57794217203996160,2">function也可以省略掉fullName(){}</d><d p="11.21700,1,25,16740868,1637288274,0,c36812c8,57775003944099328,2">2021-11-19</d><d p="60.05300,1,25,16707842,1637280460,0,21f5c3f1,57770907217181696,2">细</d><d p="38.97900,1,25,16777215,1637243737,0,18cc0530,57751653837863424,2">21点55分</d><d p="160.08400,1,25,16777215,1637167679,0,e2b1bf97,57711777269742080,2">11.18凌晨的兄弟扣个6</d><d p="31.65200,1,25,16777215,1637073213,0,64af8dd7,57662249821599744,2">22:33</d><d p="270.91600,1,25,10546688,1637072035,0,895aceed,57661632356268544,2">2022-11-16</d><d p="5.69700,1,25,16777215,1636998151,0,3ae00536,57622895924628480,2">西北孤狼</d><d p="217.17200,1,25,16777215,1636958770,0,a2a3adb9,57602249057683968,2">老师这一节说话好温柔</d><d p="112.01000,1,25,16777215,1636958662,0,a2a3adb9,57602192260715520,2">老师说话有助睡眠很难不同意</d><d p="223.92200,1,25,16777215,1636808393,0,b73a14cf,57523408007831040,2">那个说不简写的估计是小白，简直笑死个人，</d><d p="22.29800,1,25,16777215,1636616642,0,d2c94666,57422875128885760,2">吾想啸 冲冲冲</d><d p="88.23200,1,25,1192210,1636610729,0,855e5605,57419775047596544,2">= =</d><d p="236.57100,1,25,16777215,1636548956,0,af279329,57387388151020032,2">那不如多写一点</d><d p="222.56400,1,25,16777215,1636548940,0,af279329,57387379636604928,2">没什么差别感觉</d><d p="268.94100,1,25,16777215,1636518056,0,462e6afb,57371187748311552,2">讲的确实好，计算属性为什么是方法也清楚了</d><d p="122.08500,1,25,16777215,1636514390,0,67064a9e,57369265441674240,2">好困啊</d><d p="93.50700,1,25,16777215,1636377545,0,1c550dfc,57297519365927936,2">请收下我的膝盖</d><d p="244.79400,1,25,16777215,1636289789,0,746647a,57251510107723264,2">就是省略setter，还不如完成的getter，还更好别人理解</d><d p="82.24400,1,25,13369971,1636187913,0,e7f76b7,57198097921802240,2">老师讲的确实好</d><d p="58.06800,1,25,16777215,1636183120,0,e0a6f979,57195584701613568,2">脱发少女打卡20集</d><d p="27.54600,1,25,16777215,1636095588,0,94eb0340,57149692785233920,2">小孟磊学vue</d><d p="5.02800,1,25,16777215,1635877592,0,10d3477c,57035400077419520,2">有妹子吗？</d><d p="254.61900,1,25,16777215,1635758116,0,eb9e137a,56972760430728704,2">我感觉简写多了会把我自己整无了</d><d p="188.44100,1,25,16777215,1635755489,0,8809e670,56971383077923328,2">确实....还不如get()</d><d p="192.43100,1,25,16777215,1635751770,0,2abb5c14,56969433329582080,2">进一步简写</d><d p="132.95600,1,25,16777215,1635751696,0,2abb5c14,56969394298933248,2">暴露一个函数</d><d p="10.40000,1,25,16777215,1635696841,0,be53f950,56940634610886656,2">乔乔学前端冲冲冲</d><d p="261.94100,1,25,15138834,1635673326,0,52104d23,56928306193808896,2">10月31日17:41</d><d p="265.65900,1,25,16777215,1635659301,0,5f385058,56920953052714496,2">说methods的还是没听懂计算属性</d><d p="64.79600,1,25,16777215,1635590160,0,a0dff08b,56884702743316992,2">axe618</d><d p="222.01200,1,25,16777215,1635488799,0,d006ed7f,56831560879145472,2">妙啊</d><d p="69.63300,1,25,16777215,1635488681,0,d006ed7f,56831498571249152,2">妙啊</d><d p="80.87000,1,25,16646914,1635298901,0,3eb56f4d,56731999616529920,2">平平无奇发送个弹幕</d><d p="22.10500,1,25,16777215,1635211482,0,8fe6c7,56686166632767488,2">2021-10-26 老羽学vue</d><d p="274.73500,1,25,16777215,1634363312,0,43906c0a,56241481281419264,2">计算属性有缓存,可以当data用</d><d p="180.72300,1,25,16777215,1634285101,0,e0d6be52,56200476484455936,2">那还不如写get，可是少五个字母呢！</d><d p="105.19900,1,25,16777215,1634182809,0,26f5c467,56146845521993216,2">老师讲话对睡眠很有帮助</d><d p="257.52100,1,25,16777215,1633955512,0,d2700863,56027676711645184,2">最终变成了methods的样子`~`</d><d p="208.52600,1,25,16777215,1633925551,0,ff0a6019,56011968600578560,2">感觉没有必要</d><d p="29.60500,1,25,16777215,1633875691,0,53793664,55985827453317632,2">小陈曦看Vue</d><d p="128.46200,1,25,16777215,1633680015,0,77dd107a,55883236979523584,2">动物世界</d><d p="196.21800,1,25,16777215,1633519239,0,2b315f96,55798943999813632,2">讲的好好</d><d p="76.62300,1,25,16777215,1633362675,0,af60fd51,55716859559427072,2">maogepao</d><d p="259.82700,1,25,16777215,1633279038,0,d4fc6135,55673009465812992,2">计算属性只会调用一次 和methods不一样</d><d p="27.70800,1,25,16777215,1633276005,0,5c3e6ee,55671419073825280,2">露露加油看 小心哥一个脑瓜崩给你崩的找不到家</d><d p="10.75100,1,25,16777215,1633169985,0,a4fbfd83,55615834161251840,2">20个脑瓜崩</d><d p="149.34400,1,25,16777215,1633164896,0,8e5b0b0f,55613166248906240,2">这笑话好冷</d><d p="17.89900,1,25,16777215,1632918577,0,ace01274,55484024208202240,2">半天看了个get set......</d><d p="12.93700,1,25,16777215,1632800159,0,82d98b22,55421939041969152,2">饭饭 冲冲冲</d><d p="51.15700,1,25,16765698,1632757751,0,6b144243,55399704859643392,2">发个颜色弹幕</d><d p="55.94500,1,25,16777215,1632754376,0,a394e428,55397935580647936,2">小马学前端</d><d p="25.65500,1,25,16765698,1632729531,0,43f8001b,55384909437737984,2">净龙云潇前来学习</d><d p="209.08300,1,25,16777215,1632658610,0,f20dcee0,55347726767075840,2">为什么我觉得大差不差呢？？？</d><d p="0.89900,1,25,16777215,1632658222,0,f20dcee0,55347523181614592,2">天才小熊猫冲冲冲！！！</d><d p="26.23300,1,25,16777215,1632571367,0,c489297c,55301985905225728,2">小美女学前端</d><d p="122.06500,1,25,16777215,1632569734,0,bb58ad59,55301129749668864,1">fullname(){。。。}</d><d p="273.72600,1,25,16777215,1632368721,0,a568e0b5,55195740958060032,1">帮帮给你两拳</d><d p="71.20700,1,25,16777215,1632292555,0,f574b2b6,55155808183851008,1">怎么快速复制哪个文件啊</d><d p="145.37900,1,25,16777215,1632204910,0,76a12d50,55109857311467520,1">,</d><d p="252.98500,1,25,16776960,1631951337,0,9bf8d22a,54976911960976384,1">各位挺好了</d><d p="237.28800,1,25,16776960,1631951316,0,9bf8d22a,54976900916412416,1">铁山靠</d><d p="223.77200,1,25,13369971,1631951261,0,9bf8d22a,54976871680205824,1">铁山靠前来学习</d><d p="5.59300,1,25,13369971,1631950861,0,9bf8d22a,54976661958484992,1">铁山靠前来学习</d><d p="131.98500,1,25,16777215,1631778844,0,c820a8f2,54886475927463424,1">小Java猛肝vue</d><d p="135.64600,1,25,16777215,1631621981,0,eff11688,54804234179936256,1">老亚瑟第一天</d><d p="94.45900,1,25,16777215,1631528865,0,4d699139,54755414684388864,1">这个声音很想 将鬼故事中的声音</d><d p="250.73000,1,25,16777215,1631331768,0,296b55ec,54652079022562304,1">不一样，计算属性有缓存机制的</d><d p="190.10100,1,25,16777215,1631331563,0,296b55ec,54651971503105024,1">？？？</d><d p="275.60600,1,25,16777215,1631254119,0,4c75e7d4,54611368941280768,1">进度条狂奔</d><d p="52.30100,1,25,16777215,1631240365,0,6e23ea41,54604157601179648,1">看的我快累死了</d><d p="23.12200,1,25,16777215,1631028606,0,4c4e99b2,54493135168023552,1">周星星永不放弃</d><d p="160.06800,1,25,16777215,1631022454,0,6bd262e4,54489909716078592,1">其实一般就是读取</d><d p="246.11300,1,25,16777215,1630824934,0,27e7b74e,54386352088893440,1">没有set方法那不就是跟methods里面一样了么，只是用的时候不允许加括号了</d><d p="8.52300,1,25,16777215,1630399421,0,f3040c09,54163260702404608,1">进度条感人</d><d p="29.87200,1,25,16777215,1630382793,0,f7b6f031,54154543059706368,1">进度条感人啊</d><d p="219.85800,1,25,16777215,1630340007,0,2bbf5a22,54132110899832320,1">尼玛，你们啥都简写，那还要啥规则和标准啊，你自己整一套语言吧</d><d p="236.51100,1,25,16777215,1630315387,0,4df13c97,54119202800888832,1">激动了！</d><d p="171.90900,1,25,16777215,1630117149,0,4c6e42ac,54015269049779712,1">2</d><d p="152.98500,1,25,16777215,1630117134,0,4c6e42ac,54015261116442112,1">1</d><d p="104.37200,1,25,16777215,1630117094,0,4c6e42ac,54015240248193536,1">111</d><d p="198.77600,1,25,16777215,1629861484,0,b944c573,53881227058972672,1">我选择完整型，代码量算绩效，哈哈哈</d><d p="204.71200,1,25,16777215,1629722792,0,aacb62ad,53808512626296832,1">我刚开始也是这样想来着？</d><d p="13.51900,1,25,16777215,1629721825,0,5700b252,53808005570593280,1">时长感人</d><d p="268.15100,1,25,9033215,1629357601,0,b25853c3,53617047179981312,1">啦啦</d><d p="228.68300,1,25,16777215,1629357562,0,b25853c3,53617026783715840,1">啦啦</d><d p="278.79700,1,25,16777215,1629270362,0,3bb5b4,53571308865263616,1">都是vm里面的东西</d><d p="251.80600,1,25,16777215,1629270335,0,3bb5b4,53571294715779072,1">处处是坑，注意避险</d><d p="210.23300,1,25,16777215,1629270294,0,3bb5b4,53571272910649856,1">666</d><d p="172.44200,1,25,16777215,1629270255,0,3bb5b4,53571252608814080,1">当get用</d><d p="127.12000,1,25,16646914,1629189693,0,1fd42b41,53529015171152896,1">小妲己第二天</d><d p="252.87200,1,25,16777215,1629182329,0,e8f5f30f,53525154337236992,1">123</d><d p="51.69700,1,25,16777215,1629103953,0,69bf3c35,53484062501254656,1">进度条爱了</d><d p="114.58100,1,25,16777215,1629096014,0,25e0e51,53479900161737216,1">老师的声音听着贼舒服</d><d p="23.07100,1,25,16777215,1629034364,0,4a5fb4be,53447577784015872,1">20集打卡</d><d p="262.05000,1,25,16777215,1629001066,0,f69ee2af,53430119858992640,1">牛！</d><d p="21.37100,1,25,13369971,1628734032,0,619ec27c,53290117128107520,1">口hi麻醉师第2天</d><d p="12.59700,1,25,16777215,1628677546,0,50bbc995,53260502669555712,1">细快硬干 </d><d p="10.55700,1,25,16777215,1628654593,0,46cdeba5,53248468446668288,1">狗哥来学vue</d><d p="255.51900,1,25,16777215,1628642848,0,3aec7f53,53242310661765120,1">细不谈</d><d p="88.70100,1,25,16777215,1628304114,0,fe7ebec1,53064716602527744,1">沙哑了</d><d p="69.04000,1,25,16777215,1628304093,0,fe7ebec1,53064705568408064,1">磁性的嗓音</d><d p="278.00000,1,25,16777215,1628175018,0,550d4b92,52997032783440896,1">妙啊</d><d p="165.00400,1,25,16777215,1628168734,0,6cf4774c,52993738577808896,1">1</d><d p="202.48700,1,25,16777215,1628128256,0,819f212a,52945790858952711,1">把我整笑了，这相声讲的</d><d p="157.91700,1,25,16777215,1628002158,0,6e733c6,52879679195971587,1">？？？？</d><d p="179.10000,1,25,16777215,1627962211,0,58236118,52858735085223941,1">get</d><d p="155.45900,1,25,16777215,1627962187,0,58236118,52858722690531333,1">逗号</d><d p="157.63200,1,25,16777215,1627831545,0,9a6b15d9,52790228904574981,1">1</d><d p="135.45900,1,25,16777215,1627715021,0,a167c8bf,52729136526917639,1">哈哈哈哈</d><d p="117.51900,1,25,16777215,1627699215,0,2e9a8c8,52720849862524933,1">适合去讲书</d><d p="277.34700,1,25,16777215,1627576606,0,a9fe1e82,52656567223320579,1">fullName(){}，也可以这样写。更简写，哈哈</d><d p="75.69800,1,25,16777215,1627297400,0,8ed6e855,52510182687113221,1">听老师讲课老是有一种在听评书的感觉</d><d p="124.92100,1,25,16777215,1627267191,0,66c3c9,52494344814854151,1">？</d><d p="146.21400,1,25,16777215,1627143003,0,4e60faa4,52429234341675011,1">有人么</d><d p="20.39400,1,25,16777215,1627004982,0,eefbf160,52356871609647109,1">first</d></i>